src/full_adder.vhdl
library IEEE;
use IEEE.std_logic_1164.all;
use IEEE.numeric_std.all;


entity full_adder is
    port (
        a, b, cin : in std_logic;
        
        sum, cout  : out std_logic
    );
end entity;

architecture full_adder_arch of full_adder is
begin
    sum <= a xor b xor cin;
    cout <= (a and b) or (a and cin) or (b and cin);
end architecture;

src/main_tb.vhdl
library IEEE;
use IEEE.std_logic_1164.all;
use IEEE.numeric_std.all;


entity full_adder_tb is
end entity;

architecture full_adder_tb_arch of full_adder_tb is
    component full_adder is
        port (
            a, b, cin : in std_logic;
        
            sum, cout  : out std_logic
        );
    end component;

    signal a, b, cin, sum, cout : std_logic;

begin
    full_adder_instance : full_adder
        port map (
            a => a,
            b => b,
            cin => cin,
            sum => sum,
            cout => cout
        );
    
    process
    begin
        a <= '0';
        b <= '0';
        cin <= '0';
        wait for 50 ns;
        assert((sum = '0') and (cout = '0')) report "Test Failed, a = 0, b = 0, cin = 0" severity error;
        
        a <= '0';
        b <= '0';
        cin <= '1';
        wait for 50 ns;
        assert((sum = '1') and (cout = '0')) report "Test Failed, a = 0, b = 0, cin = 1" severity error;

        a <= '0';
        b <= '1';
        cin <= '0';
        wait for 50 ns;
        assert((sum = '1') and (cout = '0')) report "Test Failed, a = 0, b = 1, cin = 0" severity error;

        a <= '0';
        b <= '1';
        cin <= '1';
        wait for 50 ns;
        assert((sum = '0') and (cout = '1')) report "Test Failed, a = 0, b = 1, cin = 1" severity error;

        a <= '1';
        b <= '0';
        cin <= '0';
        wait for 50 ns;
        assert((sum = '1') and (cout = '0')) report "Test Failed, a = 1, b = 0, cin = 0" severity error;

        a <= '1';
        b <= '0';
        cin <= '1';
        wait for 50 ns;
        assert((sum = '0') and (cout = '1')) report "Test Failed, a = 1, b = 0, cin = 1" severity error;

        a <= '1';
        b <= '1';
        cin <= '0';
        wait for 50 ns;
        assert((sum = '0') and (cout = '1')) report "Test Failed, a = 1, b = 1, cin = 0" severity error;

        a <= '1';
        b <= '1';
        cin <= '1';
        wait for 50 ns;
        assert((sum = '1') and (cout = '1')) report "Test Failed, a = 1, b = 1, cin = 1" severity error;

    end process;
end architecture;

build/main_tb.vcd
$date
  Tue Oct 27 21:23:46 2020
$end
$version
  GHDL v0
$end
$timescale
  1 fs
$end
$scope module standard $end
$upscope $end
$scope module std_logic_1164 $end
$upscope $end
$scope module numeric_std $end
$upscope $end
$scope module full_adder_tb $end
$var reg 1 ! a $end
$var reg 1 " b $end
$var reg 1 # cin $end
$var reg 1 $ sum $end
$var reg 1 % cout $end
$scope module full_adder_instance $end
$var reg 1 & a $end
$var reg 1 ' b $end
$var reg 1 ( cin $end
$var reg 1 ) sum $end
$var reg 1 * cout $end
$upscope $end
$upscope $end
$enddefinitions $end
#0
0!
0"
0#
0$
0%
0&
0'
0(
0)
0*
#50000000
1#
1$
1(
1)
#100000000
1"
0#
1'
0(
#150000000
1#
0$
1%
1(
0)
1*
#200000000
1!
0"
0#
1$
0%
1&
0'
0(
1)
0*
#250000000
1#
0$
1%
1(
0)
1*
#300000000
1"
0#
1'
0(
#350000000
1#
1$
1(
1)
#400000000
0!
0"
0#
0$
0%
0&
0'
0(
0)
0*
